MANIFEST.in
README.rst
setup.cfg
setup.py
InstagramPy/AppInfo.py
InstagramPy/InstagramPyCLI.py
InstagramPy/InstagramPyConfigurationCreator.py
InstagramPy/InstagramPyDumper.py
InstagramPy/InstagramPyInstance.py
InstagramPy/InstagramPyPortable.py
InstagramPy/InstagramPyScript.py
InstagramPy/InstagramPySession.py
InstagramPy/__init__.py
InstagramPy/colors/__init__.py
InstagramPy/colors/ansi.py
InstagramPy/colors/ansitowin32.py
InstagramPy/colors/initialise.py
InstagramPy/colors/win32.py
InstagramPy/colors/winterm.py