Metadata-Version: 1.1
Name: instagram-py
Version: 2.0.5
Summary: Slick Instagram brute force command line tool writen in python.
Home-page: https://github.com/antony-jr/Instagram-Py
Author: Antony-Jr
Author-email: antonyjr@protonmail.com
License: MIT
Download-URL: https://github.com/antony-jr/instagram-py/archive/v2.0.5.tar.gz
Keywords: cli,hack,instagram,with,out,password,limit,brute,force,attack,instagram
Platform: UNKNOWN
Classifier: Topic :: Utilities
Classifier: Natural Language :: English
Classifier: Operating System :: OS Independent
Classifier: Programming Language :: Python :: 3.4
Classifier: Programming Language :: Python :: 3.6
